<?xml version="1.0" encoding="UTF-8"?>

<xwikidoc>
  <web>SankoreCode</web>
  <name>ListSubjects</name>
  <language/>
  <defaultLanguage/>
  <translation>0</translation>
  <parent/>
  <creator>xwiki:XWiki.Admin</creator>
  <author>xwiki:XWiki.Admin</author>
  <customClass/>
  <contentAuthor>xwiki:XWiki.Admin</contentAuthor>
  <creationDate>1308646046000</creationDate>
  <date>1419607338000</date>
  <contentUpdateDate>1419607338000</contentUpdateDate>
  <version>1.1</version>
  <title>List subjects</title>
  <template/>
  <defaultTemplate/>
  <validationScript/>
  <comment/>
  <minorEdit>false</minorEdit>
  <syntaxId>xwiki/2.0</syntaxId>
  <hidden>false</hidden>
  <content>List of all subjects which don't have an object of type XWiki.FrameworkItemClass

{{velocity}}
#set($hql = $xwiki.searchDocuments(" ,BaseObject as obj where doc.fullName not in (select doc.fullName from XWikiDocument doc, BaseObject obj where doc.fullName=obj.name and obj.className='XWiki.FrameworkItemClass') and doc.space='FW_masterFramework' order by doc.date desc"))
#foreach ($page in $hql)
  * [[$page]]
#end
{{/velocity}}

second query
</content>
</xwikidoc>
